{
  "symbol": "In106",
  "Z": 49,
  "A": 106,
  "atomic_mass": 105.913465411,
  "half_life": {
    "value": 6.2,
    "unit": "minutes",
    "seconds": 372.0
  },
  "isomer_state": 0,
  "decay_modes": [
    {
      "mode": "ec",
      "daughter": "Cd106",
      "branching_ratio": 1.0,
      "gammas": [
        {
          "energy_keV": 161.0,
          "absolute_intensity": 0.004985,
          "intensity_percent": 0.4985,
          "id": "0",
          "coincident_gammas": [
            {
              "id": "2",
              "correlation": 0.6844
            },
            {
              "id": "32",
              "correlation": 0.529
            },
            {
              "id": "18",
              "correlation": 0.2528
            },
            {
              "id": "31",
              "correlation": 0.2777
            },
            {
              "id": "60",
              "correlation": 0.4634
            },
            {
              "id": "20",
              "correlation": 0.9873
            }
          ]
        },
        {
          "energy_keV": 186.6,
          "absolute_intensity": 0.005982,
          "intensity_percent": 0.5982000000000001,
          "id": "1",
          "coincident_gammas": [
            {
              "id": "32",
              "correlation": 0.8643
            },
            {
              "id": "29",
              "correlation": 0.8682
            },
            {
              "id": "20",
              "correlation": 0.9884
            },
            {
              "id": "68",
              "correlation": 0.1289
            }
          ]
        },
        {
          "energy_keV": 225.7,
          "absolute_intensity": 0.068793,
          "intensity_percent": 6.879300000000001,
          "id": "2",
          "coincident_gammas": [
            {
              "id": "32",
              "correlation": 0.3511
            },
            {
              "id": "18",
              "correlation": 0.3514
            },
            {
              "id": "60",
              "correlation": 0.6443
            },
            {
              "id": "20",
              "correlation": 0.99
            }
          ]
        },
        {
          "energy_keV": 282.7,
          "absolute_intensity": 0.0,
          "intensity_percent": 0.0,
          "id": "",
          "coincident_gammas": [
            {
              "id": "39",
              "correlation": 0.1122
            },
            {
              "id": "31",
              "correlation": 0.1132
            },
            {
              "id": "29",
              "correlation": 0.005881
            },
            {
              "id": "18",
              "correlation": 0.103
            },
            {
              "id": "1",
              "correlation": 0.006774
            },
            {
              "id": "16",
              "correlation": 0.4824
            },
            {
              "id": "15",
              "correlation": 0.1126
            },
            {
              "id": "68",
              "correlation": 0.000873
            },
            {
              "id": "32",
              "correlation": 0.7998
            },
            {
              "id": "20",
              "correlation": 0.9848
            },
            {
              "id": "24",
              "correlation": 0.402
            },
            {
              "id": "0",
              "correlation": 0.005645
            },
            {
              "id": "2",
              "correlation": 0.279
            },
            {
              "id": "38",
              "correlation": 0.4686
            },
            {
              "id": "60",
              "correlation": 0.1889
            }
          ]
        },
        {
          "energy_keV": 308.9,
          "absolute_intensity": 0.0,
          "intensity_percent": 0.0,
          "id": ""
        },
        {
          "energy_keV": 314.6,
          "absolute_intensity": 0.0,
          "intensity_percent": 0.0,
          "id": ""
        },
        {
          "energy_keV": 390.7,
          "absolute_intensity": 0.0,
          "intensity_percent": 0.0,
          "id": ""
        },
        {
          "energy_keV": 395.5,
          "absolute_intensity": 0.0,
          "intensity_percent": 0.0,
          "id": ""
        },
        {
          "energy_keV": 421.3,
          "absolute_intensity": 0.0,
          "intensity_percent": 0.0,
          "id": "",
          "coincident_gammas": [
            {
              "id": "60",
              "correlation": 0.001926
            },
            {
              "id": "29",
              "correlation": 0.00433
            },
            {
              "id": "38",
              "correlation": 0.345
            },
            {
              "id": "0",
              "correlation": 0.004156
            },
            {
              "id": "18",
              "correlation": 0.001051
            },
            {
              "id": "1",
              "correlation": 0.004988
            },
            {
              "id": "19",
              "correlation": 0.6393
            },
            {
              "id": "68",
              "correlation": 0.0006427
            },
            {
              "id": "32",
              "correlation": 0.987
            },
            {
              "id": "20",
              "correlation": 0.9851
            },
            {
              "id": "39",
              "correlation": 0.6399
            },
            {
              "id": "2",
              "correlation": 0.002844
            },
            {
              "id": "31",
              "correlation": 0.001154
            },
            {
              "id": "21",
              "correlation": 0.3552
            }
          ]
        },
        {
          "energy_keV": 433.1,
          "absolute_intensity": 0.022931,
          "intensity_percent": 2.2931,
          "id": "",
          "coincident_gammas": [
            {
              "id": "31",
              "correlation": 0.00325
            },
            {
              "id": "29",
              "correlation": 0.01219
            },
            {
              "id": "38",
              "correlation": 0.9713
            },
            {
              "id": "0",
              "correlation": 0.0117
            },
            {
              "id": "18",
              "correlation": 0.002958
            },
            {
              "id": "1",
              "correlation": 0.01404
            },
            {
              "id": "68",
              "correlation": 0.00181
            },
            {
              "id": "32",
              "correlation": 0.9853
            },
            {
              "id": "20",
              "correlation": 0.988
            },
            {
              "id": "2",
              "correlation": 0.008008
            },
            {
              "id": "60",
              "correlation": 0.005423
            }
          ]
        },
        {
          "energy_keV": 438.6,
          "absolute_intensity": 0.0,
          "intensity_percent": 0.0,
          "id": ""
        },
        {
          "energy_keV": 524.6,
          "absolute_intensity": 0.018943,
          "intensity_percent": 1.8943,
          "id": "",
          "coincident_gammas": [
            {
              "id": "32",
              "correlation": 0.3511
            },
            {
              "id": "18",
              "correlation": 0.3514
            },
            {
              "id": "60",
              "correlation": 0.6443
            },
            {
              "id": "20",
              "correlation": 0.99
            }
          ]
        },
        {
          "energy_keV": 541.0,
          "absolute_intensity": 0.12462,
          "intensity_percent": 12.462,
          "id": "12",
          "coincident_gammas": [
            {
              "id": "32",
              "correlation": 0.9926
            },
            {
              "id": "39",
              "correlation": 0.997
            },
            {
              "id": "20",
              "correlation": 0.9881
            }
          ]
        },
        {
          "energy_keV": 552.4,
          "absolute_intensity": 0.25124,
          "intensity_percent": 25.124000000000002,
          "id": "13",
          "coincident_gammas": [
            {
              "id": "31",
              "correlation": 0.00325
            },
            {
              "id": "29",
              "correlation": 0.01219
            },
            {
              "id": "38",
              "correlation": 0.9713
            },
            {
              "id": "0",
              "correlation": 0.0117
            },
            {
              "id": "18",
              "correlation": 0.002958
            },
            {
              "id": "1",
              "correlation": 0.01404
            },
            {
              "id": "68",
              "correlation": 0.00181
            },
            {
              "id": "32",
              "correlation": 0.9853
            },
            {
              "id": "20",
              "correlation": 0.988
            },
            {
              "id": "2",
              "correlation": 0.008008
            },
            {
              "id": "60",
              "correlation": 0.005423
            }
          ]
        },
        {
          "energy_keV": 558.6,
          "absolute_intensity": 0.021934,
          "intensity_percent": 2.1934,
          "id": "14",
          "coincident_gammas": [
            {
              "id": "73",
              "correlation": 0.3739
            },
            {
              "id": "32",
              "correlation": 0.6204
            },
            {
              "id": "20",
              "correlation": 0.9892
            },
            {
              "id": "37",
              "correlation": 0.6231
            }
          ]
        },
        {
          "energy_keV": 580.7,
          "absolute_intensity": 0.006979,
          "intensity_percent": 0.6979,
          "id": "15",
          "coincident_gammas": [
            {
              "id": "32",
              "correlation": 0.9926
            },
            {
              "id": "39",
              "correlation": 0.997
            },
            {
              "id": "20",
              "correlation": 0.9881
            }
          ]
        },
        {
          "energy_keV": 592.1,
          "absolute_intensity": 0.02991,
          "intensity_percent": 2.991,
          "id": "16",
          "coincident_gammas": [
            {
              "id": "31",
              "correlation": 0.00325
            },
            {
              "id": "29",
              "correlation": 0.01219
            },
            {
              "id": "38",
              "correlation": 0.9713
            },
            {
              "id": "0",
              "correlation": 0.0117
            },
            {
              "id": "18",
              "correlation": 0.002958
            },
            {
              "id": "1",
              "correlation": 0.01404
            },
            {
              "id": "68",
              "correlation": 0.00181
            },
            {
              "id": "32",
              "correlation": 0.9853
            },
            {
              "id": "20",
              "correlation": 0.988
            },
            {
              "id": "2",
              "correlation": 0.008008
            },
            {
              "id": "60",
              "correlation": 0.005423
            }
          ]
        },
        {
          "energy_keV": 601.4,
          "absolute_intensity": 0.0,
          "intensity_percent": 0.0,
          "id": "",
          "coincident_gammas": [
            {
              "id": "32",
              "correlation": 0.9896
            },
            {
              "id": "39",
              "correlation": 0.994
            },
            {
              "id": "45",
              "correlation": 0.9962
            },
            {
              "id": "20",
              "correlation": 0.9851
            }
          ]
        },
        {
          "energy_keV": 610.7,
          "absolute_intensity": 0.035892,
          "intensity_percent": 3.5892,
          "id": "18",
          "coincident_gammas": [
            {
              "id": "32",
              "correlation": 0.9956
            },
            {
              "id": "20",
              "correlation": 0.991
            }
          ]
        },
        {
          "energy_keV": 623.2,
          "absolute_intensity": 0.017946,
          "intensity_percent": 1.7946,
          "id": "19",
          "coincident_gammas": [
            {
              "id": "32",
              "correlation": 0.9926
            },
            {
              "id": "39",
              "correlation": 0.997
            },
            {
              "id": "20",
              "correlation": 0.9881
            }
          ]
        },
        {
          "energy_keV": 632.6,
          "absolute_intensity": 0.997,
          "intensity_percent": 99.7,
          "id": "20"
        },
        {
          "energy_keV": 634.1,
          "absolute_intensity": 0.00997,
          "intensity_percent": 0.997,
          "id": "21",
          "coincident_gammas": [
            {
              "id": "31",
              "correlation": 0.00325
            },
            {
              "id": "29",
              "correlation": 0.01219
            },
            {
              "id": "38",
              "correlation": 0.9713
            },
            {
              "id": "0",
              "correlation": 0.0117
            },
            {
              "id": "18",
              "correlation": 0.002958
            },
            {
              "id": "1",
              "correlation": 0.01404
            },
            {
              "id": "68",
              "correlation": 0.00181
            },
            {
              "id": "32",
              "correlation": 0.9853
            },
            {
              "id": "20",
              "correlation": 0.988
            },
            {
              "id": "2",
              "correlation": 0.008008
            },
            {
              "id": "60",
              "correlation": 0.005423
            }
          ]
        },
        {
          "energy_keV": 636.2,
          "absolute_intensity": 0.0,
          "intensity_percent": 0.0,
          "id": ""
        },
        {
          "energy_keV": 690.9,
          "absolute_intensity": 0.0,
          "intensity_percent": 0.0,
          "id": ""
        },
        {
          "energy_keV": 753.3,
          "absolute_intensity": 0.024925,
          "intensity_percent": 2.4924999999999997,
          "id": "24",
          "coincident_gammas": [
            {
              "id": "2",
              "correlation": 0.6844
            },
            {
              "id": "32",
              "correlation": 0.529
            },
            {
              "id": "18",
              "correlation": 0.2528
            },
            {
              "id": "31",
              "correlation": 0.2777
            },
            {
              "id": "60",
              "correlation": 0.4634
            },
            {
              "id": "20",
              "correlation": 0.9873
            }
          ]
        },
        {
          "energy_keV": 780.7,
          "absolute_intensity": 0.0,
          "intensity_percent": 0.0,
          "id": "",
          "coincident_gammas": [
            {
              "id": "32",
              "correlation": 0.9926
            },
            {
              "id": "39",
              "correlation": 0.997
            },
            {
              "id": "20",
              "correlation": 0.9881
            }
          ]
        },
        {
          "energy_keV": 792.5,
          "absolute_intensity": 0.0,
          "intensity_percent": 0.0,
          "id": "",
          "coincident_gammas": [
            {
              "id": "31",
              "correlation": 0.00325
            },
            {
              "id": "29",
              "correlation": 0.01219
            },
            {
              "id": "38",
              "correlation": 0.9713
            },
            {
              "id": "0",
              "correlation": 0.0117
            },
            {
              "id": "18",
              "correlation": 0.002958
            },
            {
              "id": "1",
              "correlation": 0.01404
            },
            {
              "id": "68",
              "correlation": 0.00181
            },
            {
              "id": "32",
              "correlation": 0.9853
            },
            {
              "id": "20",
              "correlation": 0.988
            },
            {
              "id": "2",
              "correlation": 0.008008
            },
            {
              "id": "60",
              "correlation": 0.005423
            }
          ]
        },
        {
          "energy_keV": 802.1,
          "absolute_intensity": 0.0,
          "intensity_percent": 0.0,
          "id": ""
        },
        {
          "energy_keV": 808.3,
          "absolute_intensity": 0.0,
          "intensity_percent": 0.0,
          "id": ""
        },
        {
          "energy_keV": 811.1,
          "absolute_intensity": 0.012762,
          "intensity_percent": 1.2762,
          "id": "29",
          "coincident_gammas": [
            {
              "id": "32",
              "correlation": 0.9956
            },
            {
              "id": "20",
              "correlation": 0.991
            }
          ]
        },
        {
          "energy_keV": 820.3,
          "absolute_intensity": 0.0,
          "intensity_percent": 0.0,
          "id": "",
          "coincident_gammas": [
            {
              "id": "32",
              "correlation": 0.3511
            },
            {
              "id": "18",
              "correlation": 0.3514
            },
            {
              "id": "60",
              "correlation": 0.6443
            },
            {
              "id": "20",
              "correlation": 0.99
            }
          ]
        },
        {
          "energy_keV": 836.7,
          "absolute_intensity": 0.027916,
          "intensity_percent": 2.7916,
          "id": "31",
          "coincident_gammas": [
            {
              "id": "32",
              "correlation": 0.9956
            },
            {
              "id": "20",
              "correlation": 0.991
            }
          ]
        },
        {
          "energy_keV": 861.1,
          "absolute_intensity": 0.8973,
          "intensity_percent": 89.73,
          "id": "32",
          "coincident_gammas": [
            {
              "id": "20",
              "correlation": 0.994
            }
          ]
        },
        {
          "energy_keV": 875.2,
          "absolute_intensity": 0.0,
          "intensity_percent": 0.0,
          "id": "",
          "coincident_gammas": [
            {
              "id": "31",
              "correlation": 0.00325
            },
            {
              "id": "29",
              "correlation": 0.01219
            },
            {
              "id": "38",
              "correlation": 0.9713
            },
            {
              "id": "0",
              "correlation": 0.0117
            },
            {
              "id": "18",
              "correlation": 0.002958
            },
            {
              "id": "1",
              "correlation": 0.01404
            },
            {
              "id": "68",
              "correlation": 0.00181
            },
            {
              "id": "32",
              "correlation": 0.9853
            },
            {
              "id": "20",
              "correlation": 0.988
            },
            {
              "id": "2",
              "correlation": 0.008008
            },
            {
              "id": "60",
              "correlation": 0.005423
            }
          ]
        },
        {
          "energy_keV": 887.1,
          "absolute_intensity": 0.0,
          "intensity_percent": 0.0,
          "id": ""
        },
        {
          "energy_keV": 974.6,
          "absolute_intensity": 0.015952,
          "intensity_percent": 1.5952000000000002,
          "id": "",
          "coincident_gammas": [
            {
              "id": "32",
              "correlation": 0.9956
            },
            {
              "id": "20",
              "correlation": 0.991
            }
          ]
        },
        {
          "energy_keV": 980.8,
          "absolute_intensity": 0.0,
          "intensity_percent": 0.0,
          "id": "",
          "coincident_gammas": [
            {
              "id": "31",
              "correlation": 0.00325
            },
            {
              "id": "29",
              "correlation": 0.01219
            },
            {
              "id": "38",
              "correlation": 0.9713
            },
            {
              "id": "0",
              "correlation": 0.0117
            },
            {
              "id": "18",
              "correlation": 0.002958
            },
            {
              "id": "1",
              "correlation": 0.01404
            },
            {
              "id": "68",
              "correlation": 0.00181
            },
            {
              "id": "32",
              "correlation": 0.9853
            },
            {
              "id": "20",
              "correlation": 0.988
            },
            {
              "id": "2",
              "correlation": 0.008008
            },
            {
              "id": "60",
              "correlation": 0.005423
            }
          ]
        },
        {
          "energy_keV": 992.1,
          "absolute_intensity": 0.014955,
          "intensity_percent": 1.4955,
          "id": "37",
          "coincident_gammas": [
            {
              "id": "32",
              "correlation": 0.9956
            },
            {
              "id": "20",
              "correlation": 0.991
            }
          ]
        },
        {
          "energy_keV": 997.8,
          "absolute_intensity": 0.41376,
          "intensity_percent": 41.376000000000005,
          "id": "38",
          "coincident_gammas": [
            {
              "id": "32",
              "correlation": 0.9956
            },
            {
              "id": "20",
              "correlation": 0.991
            }
          ]
        },
        {
          "energy_keV": 1009.3,
          "absolute_intensity": 0.27418,
          "intensity_percent": 27.418,
          "id": "39",
          "coincident_gammas": [
            {
              "id": "32",
              "correlation": 0.9956
            },
            {
              "id": "20",
              "correlation": 0.991
            }
          ]
        },
        {
          "energy_keV": 1027.4,
          "absolute_intensity": 0.0,
          "intensity_percent": 0.0,
          "id": "",
          "coincident_gammas": [
            {
              "id": "2",
              "correlation": 0.6844
            },
            {
              "id": "32",
              "correlation": 0.529
            },
            {
              "id": "18",
              "correlation": 0.2528
            },
            {
              "id": "31",
              "correlation": 0.2777
            },
            {
              "id": "60",
              "correlation": 0.4634
            },
            {
              "id": "20",
              "correlation": 0.9873
            }
          ]
        },
        {
          "energy_keV": 1031.6,
          "absolute_intensity": 0.0,
          "intensity_percent": 0.0,
          "id": ""
        },
        {
          "energy_keV": 1063.7,
          "absolute_intensity": 0.0,
          "intensity_percent": 0.0,
          "id": ""
        },
        {
          "energy_keV": 1076.9,
          "absolute_intensity": 0.0,
          "intensity_percent": 0.0,
          "id": ""
        },
        {
          "energy_keV": 1135.2,
          "absolute_intensity": 0.005982,
          "intensity_percent": 0.5982000000000001,
          "id": "",
          "coincident_gammas": [
            {
              "id": "32",
              "correlation": 0.9956
            },
            {
              "id": "20",
              "correlation": 0.991
            }
          ]
        },
        {
          "energy_keV": 1139.0,
          "absolute_intensity": 0.026919,
          "intensity_percent": 2.6919,
          "id": "45",
          "coincident_gammas": [
            {
              "id": "32",
              "correlation": 0.9926
            },
            {
              "id": "39",
              "correlation": 0.997
            },
            {
              "id": "20",
              "correlation": 0.9881
            }
          ]
        },
        {
          "energy_keV": 1142.7,
          "absolute_intensity": 0.0,
          "intensity_percent": 0.0,
          "id": "",
          "coincident_gammas": [
            {
              "id": "2",
              "correlation": 0.6844
            },
            {
              "id": "32",
              "correlation": 0.529
            },
            {
              "id": "18",
              "correlation": 0.2528
            },
            {
              "id": "31",
              "correlation": 0.2777
            },
            {
              "id": "60",
              "correlation": 0.4634
            },
            {
              "id": "20",
              "correlation": 0.9873
            }
          ]
        },
        {
          "energy_keV": 1145.0,
          "absolute_intensity": 0.038883,
          "intensity_percent": 3.8883,
          "id": ""
        },
        {
          "energy_keV": 1149.4,
          "absolute_intensity": 0.0,
          "intensity_percent": 0.0,
          "id": "",
          "coincident_gammas": [
            {
              "id": "31",
              "correlation": 0.00325
            },
            {
              "id": "29",
              "correlation": 0.01219
            },
            {
              "id": "38",
              "correlation": 0.9713
            },
            {
              "id": "0",
              "correlation": 0.0117
            },
            {
              "id": "18",
              "correlation": 0.002958
            },
            {
              "id": "1",
              "correlation": 0.01404
            },
            {
              "id": "68",
              "correlation": 0.00181
            },
            {
              "id": "32",
              "correlation": 0.9853
            },
            {
              "id": "20",
              "correlation": 0.988
            },
            {
              "id": "2",
              "correlation": 0.008008
            },
            {
              "id": "60",
              "correlation": 0.005423
            }
          ]
        },
        {
          "energy_keV": 1173.7,
          "absolute_intensity": 0.0,
          "intensity_percent": 0.0,
          "id": ""
        },
        {
          "energy_keV": 1199.7,
          "absolute_intensity": 0.0,
          "intensity_percent": 0.0,
          "id": "",
          "coincident_gammas": [
            {
              "id": "39",
              "correlation": 0.3114
            },
            {
              "id": "20",
              "correlation": 0.9851
            },
            {
              "id": "13",
              "correlation": 0.6297
            },
            {
              "id": "14",
              "correlation": 0.05497
            },
            {
              "id": "68",
              "correlation": 0.001139
            },
            {
              "id": "73",
              "correlation": 0.02055
            },
            {
              "id": "60",
              "correlation": 0.003415
            },
            {
              "id": "18",
              "correlation": 0.001863
            },
            {
              "id": "38",
              "correlation": 0.6116
            },
            {
              "id": "2",
              "correlation": 0.005043
            },
            {
              "id": "0",
              "correlation": 0.007368
            },
            {
              "id": "12",
              "correlation": 0.3123
            },
            {
              "id": "29",
              "correlation": 0.007676
            },
            {
              "id": "31",
              "correlation": 0.002046
            },
            {
              "id": "32",
              "correlation": 0.9646
            },
            {
              "id": "37",
              "correlation": 0.03425
            },
            {
              "id": "1",
              "correlation": 0.008842
            }
          ]
        },
        {
          "energy_keV": 1217.5,
          "absolute_intensity": 0.0,
          "intensity_percent": 0.0,
          "id": "",
          "coincident_gammas": [
            {
              "id": "2",
              "correlation": 0.6844
            },
            {
              "id": "32",
              "correlation": 0.529
            },
            {
              "id": "18",
              "correlation": 0.2528
            },
            {
              "id": "31",
              "correlation": 0.2777
            },
            {
              "id": "60",
              "correlation": 0.4634
            },
            {
              "id": "20",
              "correlation": 0.9873
            }
          ]
        },
        {
          "energy_keV": 1243.3,
          "absolute_intensity": 0.0,
          "intensity_percent": 0.0,
          "id": ""
        },
        {
          "energy_keV": 1284.6,
          "absolute_intensity": 0.0,
          "intensity_percent": 0.0,
          "id": "",
          "coincident_gammas": [
            {
              "id": "32",
              "correlation": 0.9926
            },
            {
              "id": "39",
              "correlation": 0.997
            },
            {
              "id": "20",
              "correlation": 0.9881
            }
          ]
        },
        {
          "energy_keV": 1295.4,
          "absolute_intensity": 0.0,
          "intensity_percent": 0.0,
          "id": "",
          "coincident_gammas": [
            {
              "id": "31",
              "correlation": 0.00325
            },
            {
              "id": "29",
              "correlation": 0.01219
            },
            {
              "id": "38",
              "correlation": 0.9713
            },
            {
              "id": "0",
              "correlation": 0.0117
            },
            {
              "id": "18",
              "correlation": 0.002958
            },
            {
              "id": "1",
              "correlation": 0.01404
            },
            {
              "id": "68",
              "correlation": 0.00181
            },
            {
              "id": "32",
              "correlation": 0.9853
            },
            {
              "id": "20",
              "correlation": 0.988
            },
            {
              "id": "2",
              "correlation": 0.008008
            },
            {
              "id": "60",
              "correlation": 0.005423
            }
          ]
        },
        {
          "energy_keV": 1298.8,
          "absolute_intensity": 0.0,
          "intensity_percent": 0.0,
          "id": ""
        },
        {
          "energy_keV": 1373.6,
          "absolute_intensity": 0.0,
          "intensity_percent": 0.0,
          "id": ""
        },
        {
          "energy_keV": 1426.5,
          "absolute_intensity": 0.0,
          "intensity_percent": 0.0,
          "id": "",
          "coincident_gammas": [
            {
              "id": "32",
              "correlation": 0.9956
            },
            {
              "id": "20",
              "correlation": 0.991
            }
          ]
        },
        {
          "energy_keV": 1430.8,
          "absolute_intensity": 0.011964,
          "intensity_percent": 1.1964000000000001,
          "id": "",
          "coincident_gammas": [
            {
              "id": "32",
              "correlation": 0.9956
            },
            {
              "id": "20",
              "correlation": 0.991
            }
          ]
        },
        {
          "energy_keV": 1442.7,
          "absolute_intensity": 0.0,
          "intensity_percent": 0.0,
          "id": "",
          "coincident_gammas": [
            {
              "id": "32",
              "correlation": 0.3511
            },
            {
              "id": "18",
              "correlation": 0.3514
            },
            {
              "id": "60",
              "correlation": 0.6443
            },
            {
              "id": "20",
              "correlation": 0.99
            }
          ]
        },
        {
          "energy_keV": 1471.9,
          "absolute_intensity": 0.065802,
          "intensity_percent": 6.5802,
          "id": "60",
          "coincident_gammas": [
            {
              "id": "20",
              "correlation": 0.994
            }
          ]
        },
        {
          "energy_keV": 1488.7,
          "absolute_intensity": 0.0,
          "intensity_percent": 0.0,
          "id": "",
          "coincident_gammas": [
            {
              "id": "32",
              "correlation": 0.9896
            },
            {
              "id": "39",
              "correlation": 0.994
            },
            {
              "id": "45",
              "correlation": 0.9962
            },
            {
              "id": "20",
              "correlation": 0.9851
            }
          ]
        },
        {
          "energy_keV": 1505.9,
          "absolute_intensity": 0.0,
          "intensity_percent": 0.0,
          "id": ""
        },
        {
          "energy_keV": 1518.6,
          "absolute_intensity": 0.0,
          "intensity_percent": 0.0,
          "id": ""
        },
        {
          "energy_keV": 1524.9,
          "absolute_intensity": 0.0,
          "intensity_percent": 0.0,
          "id": ""
        },
        {
          "energy_keV": 1550.5,
          "absolute_intensity": 0.0,
          "intensity_percent": 0.0,
          "id": ""
        },
        {
          "energy_keV": 1622.1,
          "absolute_intensity": 0.0,
          "intensity_percent": 0.0,
          "id": ""
        },
        {
          "energy_keV": 1633.2,
          "absolute_intensity": 0.0,
          "intensity_percent": 0.0,
          "id": ""
        },
        {
          "energy_keV": 1672.6,
          "absolute_intensity": 0.0018943,
          "intensity_percent": 0.18943000000000002,
          "id": "68",
          "coincident_gammas": [
            {
              "id": "20",
              "correlation": 0.994
            }
          ]
        },
        {
          "energy_keV": 1757.1,
          "absolute_intensity": 0.0,
          "intensity_percent": 0.0,
          "id": ""
        },
        {
          "energy_keV": 1763.4,
          "absolute_intensity": 0.0,
          "intensity_percent": 0.0,
          "id": ""
        },
        {
          "energy_keV": 1780.1,
          "absolute_intensity": 0.014955,
          "intensity_percent": 1.4955,
          "id": "",
          "coincident_gammas": [
            {
              "id": "32",
              "correlation": 0.9926
            },
            {
              "id": "39",
              "correlation": 0.997
            },
            {
              "id": "20",
              "correlation": 0.9881
            }
          ]
        },
        {
          "energy_keV": 1790.4,
          "absolute_intensity": 0.003988,
          "intensity_percent": 0.39880000000000004,
          "id": "",
          "coincident_gammas": [
            {
              "id": "31",
              "correlation": 0.00325
            },
            {
              "id": "29",
              "correlation": 0.01219
            },
            {
              "id": "38",
              "correlation": 0.9713
            },
            {
              "id": "0",
              "correlation": 0.0117
            },
            {
              "id": "18",
              "correlation": 0.002958
            },
            {
              "id": "1",
              "correlation": 0.01404
            },
            {
              "id": "68",
              "correlation": 0.00181
            },
            {
              "id": "32",
              "correlation": 0.9853
            },
            {
              "id": "20",
              "correlation": 0.988
            },
            {
              "id": "2",
              "correlation": 0.008008
            },
            {
              "id": "60",
              "correlation": 0.005423
            }
          ]
        },
        {
          "energy_keV": 1853.0,
          "absolute_intensity": 0.008973,
          "intensity_percent": 0.8973,
          "id": "73",
          "coincident_gammas": [
            {
              "id": "20",
              "correlation": 0.994
            }
          ]
        },
        {
          "energy_keV": 1896.4,
          "absolute_intensity": 0.0,
          "intensity_percent": 0.0,
          "id": ""
        },
        {
          "energy_keV": 1978.9,
          "absolute_intensity": 0.0,
          "intensity_percent": 0.0,
          "id": "",
          "coincident_gammas": [
            {
              "id": "32",
              "correlation": 0.9956
            },
            {
              "id": "20",
              "correlation": 0.991
            }
          ]
        },
        {
          "energy_keV": 2005.3,
          "absolute_intensity": 0.0,
          "intensity_percent": 0.0,
          "id": ""
        },
        {
          "energy_keV": 2046.2,
          "absolute_intensity": 0.0,
          "intensity_percent": 0.0,
          "id": ""
        },
        {
          "energy_keV": 2087.1,
          "absolute_intensity": 0.0,
          "intensity_percent": 0.0,
          "id": "",
          "coincident_gammas": [
            {
              "id": "39",
              "correlation": 0.3114
            },
            {
              "id": "20",
              "correlation": 0.9851
            },
            {
              "id": "13",
              "correlation": 0.6297
            },
            {
              "id": "14",
              "correlation": 0.05497
            },
            {
              "id": "68",
              "correlation": 0.001139
            },
            {
              "id": "73",
              "correlation": 0.02055
            },
            {
              "id": "60",
              "correlation": 0.003415
            },
            {
              "id": "18",
              "correlation": 0.001863
            },
            {
              "id": "38",
              "correlation": 0.6116
            },
            {
              "id": "2",
              "correlation": 0.005043
            },
            {
              "id": "0",
              "correlation": 0.007368
            },
            {
              "id": "12",
              "correlation": 0.3123
            },
            {
              "id": "29",
              "correlation": 0.007676
            },
            {
              "id": "31",
              "correlation": 0.002046
            },
            {
              "id": "32",
              "correlation": 0.9646
            },
            {
              "id": "37",
              "correlation": 0.03425
            },
            {
              "id": "1",
              "correlation": 0.008842
            }
          ]
        },
        {
          "energy_keV": 2148.8,
          "absolute_intensity": 0.0,
          "intensity_percent": 0.0,
          "id": "",
          "coincident_gammas": [
            {
              "id": "32",
              "correlation": 0.9956
            },
            {
              "id": "20",
              "correlation": 0.991
            }
          ]
        },
        {
          "energy_keV": 2225.7,
          "absolute_intensity": 0.0,
          "intensity_percent": 0.0,
          "id": ""
        },
        {
          "energy_keV": 2390.3,
          "absolute_intensity": 0.0,
          "intensity_percent": 0.0,
          "id": ""
        },
        {
          "energy_keV": 2414.1,
          "absolute_intensity": 0.0,
          "intensity_percent": 0.0,
          "id": ""
        },
        {
          "energy_keV": 2449.0,
          "absolute_intensity": 0.0,
          "intensity_percent": 0.0,
          "id": ""
        },
        {
          "energy_keV": 2494.3,
          "absolute_intensity": 0.0,
          "intensity_percent": 0.0,
          "id": ""
        },
        {
          "energy_keV": 2551.4,
          "absolute_intensity": 0.0,
          "intensity_percent": 0.0,
          "id": ""
        },
        {
          "energy_keV": 2586.2,
          "absolute_intensity": 0.0,
          "intensity_percent": 0.0,
          "id": ""
        }
      ]
    }
  ],
  "_metadata": {
    "source": "sandia.decay.xml",
    "description": "Nuclear decay data from Sandia National Laboratories",
    "has_gamma_emissions": true,
    "num_decay_modes": 1,
    "num_gamma_lines": 87
  }
}