{
  "symbol": "La128",
  "Z": 57,
  "A": 128,
  "atomic_mass": 127.915585177,
  "half_life": {
    "value": 5.180000000000001,
    "unit": "minutes",
    "seconds": 310.8
  },
  "isomer_state": 0,
  "decay_modes": [
    {
      "mode": "ec",
      "daughter": "Ba128",
      "branching_ratio": 1.0,
      "gammas": [
        {
          "energy_keV": 249.8,
          "absolute_intensity": 0.0033478,
          "intensity_percent": 0.33478,
          "id": "",
          "coincident_gammas": [
            {
              "id": "60",
              "correlation": 0.881
            },
            {
              "id": "7",
              "correlation": 0.7676
            },
            {
              "id": "1",
              "correlation": 0.6488
            }
          ]
        },
        {
          "energy_keV": 284.1,
          "absolute_intensity": 0.881,
          "intensity_percent": 88.1,
          "id": "1"
        },
        {
          "energy_keV": 315.8,
          "absolute_intensity": 0.0055503,
          "intensity_percent": 0.55503,
          "id": "",
          "coincident_gammas": [
            {
              "id": "4",
              "correlation": 0.07197
            },
            {
              "id": "19",
              "correlation": 0.5084
            },
            {
              "id": "54",
              "correlation": 0.3726
            },
            {
              "id": "7",
              "correlation": 0.3535
            },
            {
              "id": "18",
              "correlation": 0.03696
            },
            {
              "id": "13",
              "correlation": 0.03283
            },
            {
              "id": "33",
              "correlation": 0.02747
            },
            {
              "id": "1",
              "correlation": 0.6152
            },
            {
              "id": "39",
              "correlation": 0.3416
            }
          ]
        },
        {
          "energy_keV": 427.4,
          "absolute_intensity": 0.007048,
          "intensity_percent": 0.7048,
          "id": "3",
          "coincident_gammas": [
            {
              "id": "33",
              "correlation": 0.1284
            },
            {
              "id": "20",
              "correlation": 0.2673
            },
            {
              "id": "7",
              "correlation": 0.2329
            },
            {
              "id": "18",
              "correlation": 0.1728
            },
            {
              "id": "9",
              "correlation": 0.3384
            },
            {
              "id": "46",
              "correlation": 0.2717
            },
            {
              "id": "1",
              "correlation": 0.5684
            }
          ]
        },
        {
          "energy_keV": 439.9,
          "absolute_intensity": 0.019118,
          "intensity_percent": 1.9118,
          "id": "4",
          "coincident_gammas": [
            {
              "id": "18",
              "correlation": 0.5054
            },
            {
              "id": "1",
              "correlation": 0.4224
            },
            {
              "id": "33",
              "correlation": 0.3756
            }
          ]
        },
        {
          "energy_keV": 451.6,
          "absolute_intensity": 0.0025549,
          "intensity_percent": 0.25549,
          "id": "",
          "coincident_gammas": [
            {
              "id": "60",
              "correlation": 0.881
            },
            {
              "id": "7",
              "correlation": 0.7676
            },
            {
              "id": "1",
              "correlation": 0.6488
            }
          ]
        },
        {
          "energy_keV": 475.4,
          "absolute_intensity": 0.0095148,
          "intensity_percent": 0.95148,
          "id": "6",
          "coincident_gammas": [
            {
              "id": "4",
              "correlation": 0.1416
            },
            {
              "id": "39",
              "correlation": 0.672
            },
            {
              "id": "7",
              "correlation": 0.05677
            },
            {
              "id": "18",
              "correlation": 0.07271
            },
            {
              "id": "13",
              "correlation": 0.06459
            },
            {
              "id": "33",
              "correlation": 0.05403
            },
            {
              "id": "1",
              "correlation": 0.6704
            }
          ]
        },
        {
          "energy_keV": 479.31,
          "absolute_intensity": 0.51362,
          "intensity_percent": 51.361999999999995,
          "id": "7",
          "coincident_gammas": [
            {
              "id": "1",
              "correlation": 0.8359
            }
          ]
        },
        {
          "energy_keV": 483.1,
          "absolute_intensity": 0.0067837,
          "intensity_percent": 0.67837,
          "id": "",
          "coincident_gammas": [
            {
              "id": "23",
              "correlation": 0.7762
            },
            {
              "id": "7",
              "correlation": 0.6763
            },
            {
              "id": "1",
              "correlation": 0.5716
            },
            {
              "id": "36",
              "correlation": 0.881
            }
          ]
        },
        {
          "energy_keV": 487.9,
          "absolute_intensity": 0.096029,
          "intensity_percent": 9.6029,
          "id": "9",
          "coincident_gammas": [
            {
              "id": "18",
              "correlation": 0.5054
            },
            {
              "id": "1",
              "correlation": 0.4224
            },
            {
              "id": "33",
              "correlation": 0.3756
            }
          ]
        },
        {
          "energy_keV": 493.9,
          "absolute_intensity": 0.010924,
          "intensity_percent": 1.0924,
          "id": "",
          "coincident_gammas": [
            {
              "id": "4",
              "correlation": 0.07197
            },
            {
              "id": "19",
              "correlation": 0.5084
            },
            {
              "id": "54",
              "correlation": 0.3726
            },
            {
              "id": "7",
              "correlation": 0.3535
            },
            {
              "id": "18",
              "correlation": 0.03696
            },
            {
              "id": "13",
              "correlation": 0.03283
            },
            {
              "id": "33",
              "correlation": 0.02747
            },
            {
              "id": "1",
              "correlation": 0.6152
            },
            {
              "id": "39",
              "correlation": 0.3416
            }
          ]
        },
        {
          "energy_keV": 531.3,
          "absolute_intensity": 0.0039645,
          "intensity_percent": 0.39645,
          "id": "11",
          "coincident_gammas": [
            {
              "id": "23",
              "correlation": 0.881
            },
            {
              "id": "7",
              "correlation": 0.7676
            },
            {
              "id": "1",
              "correlation": 0.6488
            }
          ]
        },
        {
          "energy_keV": 531.7,
          "absolute_intensity": 0.003524,
          "intensity_percent": 0.3524,
          "id": "",
          "coincident_gammas": [
            {
              "id": "4",
              "correlation": 0.004794
            },
            {
              "id": "39",
              "correlation": 0.02275
            },
            {
              "id": "75",
              "correlation": 0.07584
            },
            {
              "id": "52",
              "correlation": 0.02709
            },
            {
              "id": "22",
              "correlation": 0.4219
            },
            {
              "id": "7",
              "correlation": 0.6066
            },
            {
              "id": "18",
              "correlation": 0.01615
            },
            {
              "id": "23",
              "correlation": 0.3717
            },
            {
              "id": "13",
              "correlation": 0.002187
            },
            {
              "id": "33",
              "correlation": 0.012
            },
            {
              "id": "1",
              "correlation": 0.6086
            },
            {
              "id": "27",
              "correlation": 0.03386
            },
            {
              "id": "56",
              "correlation": 0.3223
            }
          ]
        },
        {
          "energy_keV": 561.0,
          "absolute_intensity": 0.0087219,
          "intensity_percent": 0.8721899999999999,
          "id": "13",
          "coincident_gammas": [
            {
              "id": "7",
              "correlation": 0.8713
            },
            {
              "id": "1",
              "correlation": 0.7364
            }
          ]
        },
        {
          "energy_keV": 567.0,
          "absolute_intensity": 0.035945,
          "intensity_percent": 3.5944999999999996,
          "id": "14",
          "coincident_gammas": [
            {
              "id": "33",
              "correlation": 0.1284
            },
            {
              "id": "20",
              "correlation": 0.2673
            },
            {
              "id": "7",
              "correlation": 0.2329
            },
            {
              "id": "18",
              "correlation": 0.1728
            },
            {
              "id": "9",
              "correlation": 0.3384
            },
            {
              "id": "46",
              "correlation": 0.2717
            },
            {
              "id": "1",
              "correlation": 0.5684
            }
          ]
        },
        {
          "energy_keV": 570.6,
          "absolute_intensity": 0.0029954,
          "intensity_percent": 0.29954000000000003,
          "id": "",
          "coincident_gammas": [
            {
              "id": "60",
              "correlation": 0.881
            },
            {
              "id": "7",
              "correlation": 0.7676
            },
            {
              "id": "1",
              "correlation": 0.6488
            }
          ]
        },
        {
          "energy_keV": 587.3,
          "absolute_intensity": 0.0076647,
          "intensity_percent": 0.76647,
          "id": "",
          "coincident_gammas": [
            {
              "id": "4",
              "correlation": 0.004794
            },
            {
              "id": "39",
              "correlation": 0.02275
            },
            {
              "id": "75",
              "correlation": 0.07584
            },
            {
              "id": "52",
              "correlation": 0.02709
            },
            {
              "id": "22",
              "correlation": 0.4219
            },
            {
              "id": "7",
              "correlation": 0.6066
            },
            {
              "id": "18",
              "correlation": 0.01615
            },
            {
              "id": "23",
              "correlation": 0.3717
            },
            {
              "id": "13",
              "correlation": 0.002187
            },
            {
              "id": "33",
              "correlation": 0.012
            },
            {
              "id": "1",
              "correlation": 0.6086
            },
            {
              "id": "27",
              "correlation": 0.03386
            },
            {
              "id": "56",
              "correlation": 0.3223
            }
          ]
        },
        {
          "energy_keV": 591.7,
          "absolute_intensity": 0.00881,
          "intensity_percent": 0.881,
          "id": "",
          "coincident_gammas": [
            {
              "id": "65",
              "correlation": 0.2182
            },
            {
              "id": "44",
              "correlation": 0.6628
            },
            {
              "id": "7",
              "correlation": 0.5775
            },
            {
              "id": "1",
              "correlation": 0.6705
            }
          ]
        },
        {
          "energy_keV": 600.5,
          "absolute_intensity": 0.096029,
          "intensity_percent": 9.6029,
          "id": "18",
          "coincident_gammas": [
            {
              "id": "1",
              "correlation": 0.8359
            }
          ]
        },
        {
          "energy_keV": 606.9,
          "absolute_intensity": 0.01947,
          "intensity_percent": 1.947,
          "id": "19",
          "coincident_gammas": [
            {
              "id": "4",
              "correlation": 0.1416
            },
            {
              "id": "39",
              "correlation": 0.672
            },
            {
              "id": "7",
              "correlation": 0.05677
            },
            {
              "id": "18",
              "correlation": 0.07271
            },
            {
              "id": "13",
              "correlation": 0.06459
            },
            {
              "id": "33",
              "correlation": 0.05403
            },
            {
              "id": "1",
              "correlation": 0.6704
            }
          ]
        },
        {
          "energy_keV": 609.0,
          "absolute_intensity": 0.075854,
          "intensity_percent": 7.585400000000001,
          "id": "20",
          "coincident_gammas": [
            {
              "id": "7",
              "correlation": 0.8713
            },
            {
              "id": "1",
              "correlation": 0.7364
            }
          ]
        },
        {
          "energy_keV": 626.0,
          "absolute_intensity": 0.034007,
          "intensity_percent": 3.4007,
          "id": "",
          "coincident_gammas": [
            {
              "id": "4",
              "correlation": 0.01823
            },
            {
              "id": "39",
              "correlation": 0.08652
            },
            {
              "id": "33",
              "correlation": 0.1598
            },
            {
              "id": "9",
              "correlation": 0.03228
            },
            {
              "id": "20",
              "correlation": 0.0255
            },
            {
              "id": "46",
              "correlation": 0.02591
            },
            {
              "id": "34",
              "correlation": 0.3743
            },
            {
              "id": "7",
              "correlation": 0.2051
            },
            {
              "id": "18",
              "correlation": 0.215
            },
            {
              "id": "38",
              "correlation": 0.2015
            },
            {
              "id": "13",
              "correlation": 0.008316
            },
            {
              "id": "6",
              "correlation": 0.1288
            },
            {
              "id": "64",
              "correlation": 0.08107
            },
            {
              "id": "1",
              "correlation": 0.5148
            },
            {
              "id": "3",
              "correlation": 0.09537
            }
          ]
        },
        {
          "energy_keV": 632.5,
          "absolute_intensity": 0.054886,
          "intensity_percent": 5.4886,
          "id": "22",
          "coincident_gammas": [
            {
              "id": "23",
              "correlation": 0.881
            },
            {
              "id": "7",
              "correlation": 0.7676
            },
            {
              "id": "1",
              "correlation": 0.6488
            }
          ]
        },
        {
          "energy_keV": 643.6,
          "absolute_intensity": 0.13303,
          "intensity_percent": 13.303,
          "id": "23",
          "coincident_gammas": [
            {
              "id": "7",
              "correlation": 0.8713
            },
            {
              "id": "1",
              "correlation": 0.7364
            }
          ]
        },
        {
          "energy_keV": 673.0,
          "absolute_intensity": 0.0030835,
          "intensity_percent": 0.30835,
          "id": "",
          "coincident_gammas": [
            {
              "id": "60",
              "correlation": 0.881
            },
            {
              "id": "7",
              "correlation": 0.7676
            },
            {
              "id": "1",
              "correlation": 0.6488
            }
          ]
        },
        {
          "energy_keV": 675.7,
          "absolute_intensity": 0.0060789,
          "intensity_percent": 0.60789,
          "id": ""
        },
        {
          "energy_keV": 681.9,
          "absolute_intensity": 0.0071361,
          "intensity_percent": 0.7136100000000001,
          "id": ""
        },
        {
          "energy_keV": 715.2,
          "absolute_intensity": 0.004405,
          "intensity_percent": 0.4405,
          "id": "27",
          "coincident_gammas": [
            {
              "id": "4",
              "correlation": 0.1416
            },
            {
              "id": "39",
              "correlation": 0.672
            },
            {
              "id": "7",
              "correlation": 0.05677
            },
            {
              "id": "18",
              "correlation": 0.07271
            },
            {
              "id": "13",
              "correlation": 0.06459
            },
            {
              "id": "33",
              "correlation": 0.05403
            },
            {
              "id": "1",
              "correlation": 0.6704
            }
          ]
        },
        {
          "energy_keV": 774.8,
          "absolute_intensity": 0.011629,
          "intensity_percent": 1.1629,
          "id": "",
          "coincident_gammas": [
            {
              "id": "18",
              "correlation": 0.08957
            },
            {
              "id": "58",
              "correlation": 0.1772
            },
            {
              "id": "61",
              "correlation": 0.4058
            },
            {
              "id": "33",
              "correlation": 0.06656
            },
            {
              "id": "7",
              "correlation": 0.3536
            },
            {
              "id": "1",
              "correlation": 0.6228
            },
            {
              "id": "78",
              "correlation": 0.298
            }
          ]
        },
        {
          "energy_keV": 781.8,
          "absolute_intensity": 0.0034359,
          "intensity_percent": 0.34359,
          "id": "",
          "coincident_gammas": [
            {
              "id": "55",
              "correlation": 0.1857
            },
            {
              "id": "7",
              "correlation": 0.3607
            },
            {
              "id": "11",
              "correlation": 0.06907
            },
            {
              "id": "20",
              "correlation": 0.1674
            },
            {
              "id": "9",
              "correlation": 0.2119
            },
            {
              "id": "23",
              "correlation": 0.06085
            },
            {
              "id": "33",
              "correlation": 0.08044
            },
            {
              "id": "46",
              "correlation": 0.1701
            },
            {
              "id": "1",
              "correlation": 0.5375
            },
            {
              "id": "14",
              "correlation": 0.6262
            },
            {
              "id": "18",
              "correlation": 0.1082
            }
          ]
        },
        {
          "energy_keV": 793.5,
          "absolute_intensity": 0.016122,
          "intensity_percent": 1.6122,
          "id": "",
          "coincident_gammas": [
            {
              "id": "65",
              "correlation": 0.2182
            },
            {
              "id": "44",
              "correlation": 0.6628
            },
            {
              "id": "7",
              "correlation": 0.5775
            },
            {
              "id": "1",
              "correlation": 0.6705
            }
          ]
        },
        {
          "energy_keV": 827.9,
          "absolute_intensity": 0.0089862,
          "intensity_percent": 0.89862,
          "id": ""
        },
        {
          "energy_keV": 830.0,
          "absolute_intensity": 0.0,
          "intensity_percent": 0.0,
          "id": "",
          "coincident_gammas": [
            {
              "id": "33",
              "correlation": 0.1284
            },
            {
              "id": "20",
              "correlation": 0.2673
            },
            {
              "id": "7",
              "correlation": 0.2329
            },
            {
              "id": "18",
              "correlation": 0.1728
            },
            {
              "id": "9",
              "correlation": 0.3384
            },
            {
              "id": "46",
              "correlation": 0.2717
            },
            {
              "id": "1",
              "correlation": 0.5684
            }
          ]
        },
        {
          "energy_keV": 884.5,
          "absolute_intensity": 0.071361,
          "intensity_percent": 7.136099999999999,
          "id": "33"
        },
        {
          "energy_keV": 915.0,
          "absolute_intensity": 0.027663,
          "intensity_percent": 2.7663,
          "id": "34",
          "coincident_gammas": [
            {
              "id": "18",
              "correlation": 0.5054
            },
            {
              "id": "1",
              "correlation": 0.4224
            },
            {
              "id": "33",
              "correlation": 0.3756
            }
          ]
        },
        {
          "energy_keV": 938.9,
          "absolute_intensity": 0.023435,
          "intensity_percent": 2.3435,
          "id": "",
          "coincident_gammas": [
            {
              "id": "55",
              "correlation": 0.1857
            },
            {
              "id": "7",
              "correlation": 0.3607
            },
            {
              "id": "11",
              "correlation": 0.06907
            },
            {
              "id": "20",
              "correlation": 0.1674
            },
            {
              "id": "9",
              "correlation": 0.2119
            },
            {
              "id": "23",
              "correlation": 0.06085
            },
            {
              "id": "33",
              "correlation": 0.08044
            },
            {
              "id": "46",
              "correlation": 0.1701
            },
            {
              "id": "1",
              "correlation": 0.5375
            },
            {
              "id": "14",
              "correlation": 0.6262
            },
            {
              "id": "18",
              "correlation": 0.1082
            }
          ]
        },
        {
          "energy_keV": 988.6,
          "absolute_intensity": 0.014977,
          "intensity_percent": 1.4977,
          "id": "36",
          "coincident_gammas": [
            {
              "id": "23",
              "correlation": 0.881
            },
            {
              "id": "7",
              "correlation": 0.7676
            },
            {
              "id": "1",
              "correlation": 0.6488
            }
          ]
        },
        {
          "energy_keV": 1005.7,
          "absolute_intensity": 0.01022,
          "intensity_percent": 1.022,
          "id": "",
          "coincident_gammas": [
            {
              "id": "23",
              "correlation": 0.881
            },
            {
              "id": "7",
              "correlation": 0.7676
            },
            {
              "id": "1",
              "correlation": 0.6488
            }
          ]
        },
        {
          "energy_keV": 1036.3,
          "absolute_intensity": 0.014889,
          "intensity_percent": 1.4889,
          "id": "38",
          "coincident_gammas": [
            {
              "id": "7",
              "correlation": 0.8713
            },
            {
              "id": "1",
              "correlation": 0.7364
            }
          ]
        },
        {
          "energy_keV": 1040.4,
          "absolute_intensity": 0.090743,
          "intensity_percent": 9.074300000000001,
          "id": "39",
          "coincident_gammas": [
            {
              "id": "1",
              "correlation": 0.8359
            }
          ]
        },
        {
          "energy_keV": 1045.7,
          "absolute_intensity": 0.0094267,
          "intensity_percent": 0.94267,
          "id": ""
        },
        {
          "energy_keV": 1046.4,
          "absolute_intensity": 0.0019382,
          "intensity_percent": 0.19382,
          "id": "",
          "coincident_gammas": [
            {
              "id": "4",
              "correlation": 0.07197
            },
            {
              "id": "19",
              "correlation": 0.5084
            },
            {
              "id": "54",
              "correlation": 0.3726
            },
            {
              "id": "7",
              "correlation": 0.3535
            },
            {
              "id": "18",
              "correlation": 0.03696
            },
            {
              "id": "13",
              "correlation": 0.03283
            },
            {
              "id": "33",
              "correlation": 0.02747
            },
            {
              "id": "1",
              "correlation": 0.6152
            },
            {
              "id": "39",
              "correlation": 0.3416
            }
          ]
        },
        {
          "energy_keV": 1049.1,
          "absolute_intensity": 0.0016739,
          "intensity_percent": 0.16739,
          "id": "",
          "coincident_gammas": [
            {
              "id": "4",
              "correlation": 0.01823
            },
            {
              "id": "39",
              "correlation": 0.08652
            },
            {
              "id": "33",
              "correlation": 0.1598
            },
            {
              "id": "9",
              "correlation": 0.03228
            },
            {
              "id": "20",
              "correlation": 0.0255
            },
            {
              "id": "46",
              "correlation": 0.02591
            },
            {
              "id": "34",
              "correlation": 0.3743
            },
            {
              "id": "7",
              "correlation": 0.2051
            },
            {
              "id": "18",
              "correlation": 0.215
            },
            {
              "id": "38",
              "correlation": 0.2015
            },
            {
              "id": "13",
              "correlation": 0.008316
            },
            {
              "id": "6",
              "correlation": 0.1288
            },
            {
              "id": "64",
              "correlation": 0.08107
            },
            {
              "id": "1",
              "correlation": 0.5148
            },
            {
              "id": "3",
              "correlation": 0.09537
            }
          ]
        },
        {
          "energy_keV": 1053.15,
          "absolute_intensity": 0.0881,
          "intensity_percent": 8.81,
          "id": "",
          "coincident_gammas": [
            {
              "id": "33",
              "correlation": 0.1284
            },
            {
              "id": "20",
              "correlation": 0.2673
            },
            {
              "id": "7",
              "correlation": 0.2329
            },
            {
              "id": "18",
              "correlation": 0.1728
            },
            {
              "id": "9",
              "correlation": 0.3384
            },
            {
              "id": "46",
              "correlation": 0.2717
            },
            {
              "id": "1",
              "correlation": 0.5684
            }
          ]
        },
        {
          "energy_keV": 1070.4,
          "absolute_intensity": 0.042024,
          "intensity_percent": 4.2024,
          "id": "44",
          "coincident_gammas": [
            {
              "id": "7",
              "correlation": 0.8713
            },
            {
              "id": "1",
              "correlation": 0.7364
            }
          ]
        },
        {
          "energy_keV": 1079.0,
          "absolute_intensity": 0.015682,
          "intensity_percent": 1.5682,
          "id": "",
          "coincident_gammas": [
            {
              "id": "33",
              "correlation": 0.1284
            },
            {
              "id": "20",
              "correlation": 0.2673
            },
            {
              "id": "7",
              "correlation": 0.2329
            },
            {
              "id": "18",
              "correlation": 0.1728
            },
            {
              "id": "9",
              "correlation": 0.3384
            },
            {
              "id": "46",
              "correlation": 0.2717
            },
            {
              "id": "1",
              "correlation": 0.5684
            }
          ]
        },
        {
          "energy_keV": 1088.2,
          "absolute_intensity": 0.077088,
          "intensity_percent": 7.7088,
          "id": "46",
          "coincident_gammas": [
            {
              "id": "1",
              "correlation": 0.8359
            }
          ]
        },
        {
          "energy_keV": 1096.1,
          "absolute_intensity": 0.0056384,
          "intensity_percent": 0.56384,
          "id": "",
          "coincident_gammas": [
            {
              "id": "65",
              "correlation": 0.2182
            },
            {
              "id": "44",
              "correlation": 0.6628
            },
            {
              "id": "7",
              "correlation": 0.5775
            },
            {
              "id": "1",
              "correlation": 0.6705
            }
          ]
        },
        {
          "energy_keV": 1100.9,
          "absolute_intensity": 0.041936,
          "intensity_percent": 4.1936,
          "id": "",
          "coincident_gammas": [
            {
              "id": "4",
              "correlation": 0.1416
            },
            {
              "id": "39",
              "correlation": 0.672
            },
            {
              "id": "7",
              "correlation": 0.05677
            },
            {
              "id": "18",
              "correlation": 0.07271
            },
            {
              "id": "13",
              "correlation": 0.06459
            },
            {
              "id": "33",
              "correlation": 0.05403
            },
            {
              "id": "1",
              "correlation": 0.6704
            }
          ]
        },
        {
          "energy_keV": 1124.9,
          "absolute_intensity": 0.010308,
          "intensity_percent": 1.0308,
          "id": "",
          "coincident_gammas": [
            {
              "id": "23",
              "correlation": 0.881
            },
            {
              "id": "7",
              "correlation": 0.7676
            },
            {
              "id": "1",
              "correlation": 0.6488
            }
          ]
        },
        {
          "energy_keV": 1143.8,
          "absolute_intensity": 0.012774,
          "intensity_percent": 1.2774,
          "id": "",
          "coincident_gammas": [
            {
              "id": "65",
              "correlation": 0.2182
            },
            {
              "id": "44",
              "correlation": 0.6628
            },
            {
              "id": "7",
              "correlation": 0.5775
            },
            {
              "id": "1",
              "correlation": 0.6705
            }
          ]
        },
        {
          "energy_keV": 1144.2,
          "absolute_intensity": 0.015682,
          "intensity_percent": 1.5682,
          "id": "",
          "coincident_gammas": [
            {
              "id": "7",
              "correlation": 0.8713
            },
            {
              "id": "1",
              "correlation": 0.7364
            }
          ]
        },
        {
          "energy_keV": 1154.3,
          "absolute_intensity": 0.003524,
          "intensity_percent": 0.3524,
          "id": "52",
          "coincident_gammas": [
            {
              "id": "18",
              "correlation": 0.5054
            },
            {
              "id": "1",
              "correlation": 0.4224
            },
            {
              "id": "33",
              "correlation": 0.3756
            }
          ]
        },
        {
          "energy_keV": 1164.9,
          "absolute_intensity": 0.0066075,
          "intensity_percent": 0.66075,
          "id": "",
          "coincident_gammas": [
            {
              "id": "23",
              "correlation": 0.881
            },
            {
              "id": "7",
              "correlation": 0.7676
            },
            {
              "id": "1",
              "correlation": 0.6488
            }
          ]
        },
        {
          "energy_keV": 1168.0,
          "absolute_intensity": 0.014272,
          "intensity_percent": 1.4272,
          "id": "54",
          "coincident_gammas": [
            {
              "id": "7",
              "correlation": 0.8713
            },
            {
              "id": "1",
              "correlation": 0.7364
            }
          ]
        },
        {
          "energy_keV": 1176.5,
          "absolute_intensity": 0.01066,
          "intensity_percent": 1.0659999999999998,
          "id": "55",
          "coincident_gammas": [
            {
              "id": "7",
              "correlation": 0.8713
            },
            {
              "id": "1",
              "correlation": 0.7364
            }
          ]
        },
        {
          "energy_keV": 1276.1,
          "absolute_intensity": 0.041936,
          "intensity_percent": 4.1936,
          "id": "56",
          "coincident_gammas": [
            {
              "id": "7",
              "correlation": 0.8713
            },
            {
              "id": "1",
              "correlation": 0.7364
            }
          ]
        },
        {
          "energy_keV": 1302.6,
          "absolute_intensity": 0.011894,
          "intensity_percent": 1.1894,
          "id": "",
          "coincident_gammas": [
            {
              "id": "4",
              "correlation": 0.1416
            },
            {
              "id": "39",
              "correlation": 0.672
            },
            {
              "id": "7",
              "correlation": 0.05677
            },
            {
              "id": "18",
              "correlation": 0.07271
            },
            {
              "id": "13",
              "correlation": 0.06459
            },
            {
              "id": "33",
              "correlation": 0.05403
            },
            {
              "id": "1",
              "correlation": 0.6704
            }
          ]
        },
        {
          "energy_keV": 1318.9,
          "absolute_intensity": 0.0060789,
          "intensity_percent": 0.60789,
          "id": "58",
          "coincident_gammas": [
            {
              "id": "18",
              "correlation": 0.5054
            },
            {
              "id": "1",
              "correlation": 0.4224
            },
            {
              "id": "33",
              "correlation": 0.3756
            }
          ]
        },
        {
          "energy_keV": 1348.4,
          "absolute_intensity": 0.0059908,
          "intensity_percent": 0.5990800000000001,
          "id": "",
          "coincident_gammas": [
            {
              "id": "33",
              "correlation": 0.1284
            },
            {
              "id": "20",
              "correlation": 0.2673
            },
            {
              "id": "7",
              "correlation": 0.2329
            },
            {
              "id": "18",
              "correlation": 0.1728
            },
            {
              "id": "9",
              "correlation": 0.3384
            },
            {
              "id": "46",
              "correlation": 0.2717
            },
            {
              "id": "1",
              "correlation": 0.5684
            }
          ]
        },
        {
          "energy_keV": 1412.3,
          "absolute_intensity": 0.033037,
          "intensity_percent": 3.3036999999999996,
          "id": "60",
          "coincident_gammas": [
            {
              "id": "7",
              "correlation": 0.8713
            },
            {
              "id": "1",
              "correlation": 0.7364
            }
          ]
        },
        {
          "energy_keV": 1440.0,
          "absolute_intensity": 0.01392,
          "intensity_percent": 1.392,
          "id": "61",
          "coincident_gammas": [
            {
              "id": "7",
              "correlation": 0.8713
            },
            {
              "id": "1",
              "correlation": 0.7364
            }
          ]
        },
        {
          "energy_keV": 1482.8,
          "absolute_intensity": 0.0050217,
          "intensity_percent": 0.50217,
          "id": "",
          "coincident_gammas": [
            {
              "id": "7",
              "correlation": 0.8713
            },
            {
              "id": "1",
              "correlation": 0.7364
            }
          ]
        },
        {
          "energy_keV": 1505.9,
          "absolute_intensity": 0.032333,
          "intensity_percent": 3.2333,
          "id": "",
          "coincident_gammas": [
            {
              "id": "33",
              "correlation": 0.1284
            },
            {
              "id": "20",
              "correlation": 0.2673
            },
            {
              "id": "7",
              "correlation": 0.2329
            },
            {
              "id": "18",
              "correlation": 0.1728
            },
            {
              "id": "9",
              "correlation": 0.3384
            },
            {
              "id": "46",
              "correlation": 0.2717
            },
            {
              "id": "1",
              "correlation": 0.5684
            }
          ]
        },
        {
          "energy_keV": 1515.3,
          "absolute_intensity": 0.0059908,
          "intensity_percent": 0.5990800000000001,
          "id": "64",
          "coincident_gammas": [
            {
              "id": "1",
              "correlation": 0.8359
            }
          ]
        },
        {
          "energy_keV": 1549.7,
          "absolute_intensity": 0.013832,
          "intensity_percent": 1.3832,
          "id": "65",
          "coincident_gammas": [
            {
              "id": "1",
              "correlation": 0.8359
            }
          ]
        },
        {
          "energy_keV": 1605.4,
          "absolute_intensity": 0.012598,
          "intensity_percent": 1.2598,
          "id": "",
          "coincident_gammas": [
            {
              "id": "33",
              "correlation": 0.1284
            },
            {
              "id": "20",
              "correlation": 0.2673
            },
            {
              "id": "7",
              "correlation": 0.2329
            },
            {
              "id": "18",
              "correlation": 0.1728
            },
            {
              "id": "9",
              "correlation": 0.3384
            },
            {
              "id": "46",
              "correlation": 0.2717
            },
            {
              "id": "1",
              "correlation": 0.5684
            }
          ]
        },
        {
          "energy_keV": 1654.1,
          "absolute_intensity": 0.0037883,
          "intensity_percent": 0.37883,
          "id": "",
          "coincident_gammas": [
            {
              "id": "4",
              "correlation": 0.1416
            },
            {
              "id": "39",
              "correlation": 0.672
            },
            {
              "id": "7",
              "correlation": 0.05677
            },
            {
              "id": "18",
              "correlation": 0.07271
            },
            {
              "id": "13",
              "correlation": 0.06459
            },
            {
              "id": "33",
              "correlation": 0.05403
            },
            {
              "id": "1",
              "correlation": 0.6704
            }
          ]
        },
        {
          "energy_keV": 1662.3,
          "absolute_intensity": 0.0086338,
          "intensity_percent": 0.86338,
          "id": "",
          "coincident_gammas": [
            {
              "id": "7",
              "correlation": 0.8713
            },
            {
              "id": "1",
              "correlation": 0.7364
            }
          ]
        },
        {
          "energy_keV": 1688.2,
          "absolute_intensity": 0.0044931,
          "intensity_percent": 0.44931,
          "id": "",
          "coincident_gammas": [
            {
              "id": "7",
              "correlation": 0.8713
            },
            {
              "id": "1",
              "correlation": 0.7364
            }
          ]
        },
        {
          "energy_keV": 1710.0,
          "absolute_intensity": 0.0027311,
          "intensity_percent": 0.27311,
          "id": "",
          "coincident_gammas": [
            {
              "id": "23",
              "correlation": 0.881
            },
            {
              "id": "7",
              "correlation": 0.7676
            },
            {
              "id": "1",
              "correlation": 0.6488
            }
          ]
        },
        {
          "energy_keV": 1710.7,
          "absolute_intensity": 0.0037002,
          "intensity_percent": 0.37001999999999996,
          "id": "",
          "coincident_gammas": [
            {
              "id": "7",
              "correlation": 0.8713
            },
            {
              "id": "1",
              "correlation": 0.7364
            }
          ]
        },
        {
          "energy_keV": 1722.8,
          "absolute_intensity": 0.0030835,
          "intensity_percent": 0.30835,
          "id": ""
        },
        {
          "energy_keV": 1724.9,
          "absolute_intensity": 0.0053741,
          "intensity_percent": 0.5374099999999999,
          "id": "",
          "coincident_gammas": [
            {
              "id": "1",
              "correlation": 0.8359
            }
          ]
        },
        {
          "energy_keV": 1726.6,
          "absolute_intensity": 0.0062551,
          "intensity_percent": 0.62551,
          "id": ""
        },
        {
          "energy_keV": 1755.5,
          "absolute_intensity": 0.0098672,
          "intensity_percent": 0.9867199999999999,
          "id": "75",
          "coincident_gammas": [
            {
              "id": "1",
              "correlation": 0.8359
            }
          ]
        },
        {
          "energy_keV": 1906.2,
          "absolute_intensity": 0.0050217,
          "intensity_percent": 0.50217,
          "id": "",
          "coincident_gammas": [
            {
              "id": "7",
              "correlation": 0.8713
            },
            {
              "id": "1",
              "correlation": 0.7364
            }
          ]
        },
        {
          "energy_keV": 1908.5,
          "absolute_intensity": 0.0057265,
          "intensity_percent": 0.57265,
          "id": "",
          "coincident_gammas": [
            {
              "id": "1",
              "correlation": 0.8359
            }
          ]
        },
        {
          "energy_keV": 1919.6,
          "absolute_intensity": 0.01022,
          "intensity_percent": 1.022,
          "id": "78",
          "coincident_gammas": [
            {
              "id": "1",
              "correlation": 0.8359
            }
          ]
        },
        {
          "energy_keV": 1957.7,
          "absolute_intensity": 0.005286,
          "intensity_percent": 0.5286,
          "id": "",
          "coincident_gammas": [
            {
              "id": "7",
              "correlation": 0.8713
            },
            {
              "id": "1",
              "correlation": 0.7364
            }
          ]
        },
        {
          "energy_keV": 2025.5,
          "absolute_intensity": 0.0034359,
          "intensity_percent": 0.34359,
          "id": ""
        },
        {
          "energy_keV": 2177.6,
          "absolute_intensity": 0.004405,
          "intensity_percent": 0.4405,
          "id": ""
        },
        {
          "energy_keV": 2191.0,
          "absolute_intensity": 0.0032597,
          "intensity_percent": 0.32597,
          "id": ""
        },
        {
          "energy_keV": 2212.0,
          "absolute_intensity": 0.0085457,
          "intensity_percent": 0.8545699999999999,
          "id": "",
          "coincident_gammas": [
            {
              "id": "7",
              "correlation": 0.8713
            },
            {
              "id": "1",
              "correlation": 0.7364
            }
          ]
        },
        {
          "energy_keV": 386.0,
          "absolute_intensity": 0.015946,
          "intensity_percent": 1.5945999999999998,
          "id": ""
        },
        {
          "energy_keV": 412.0,
          "absolute_intensity": 0.0093386,
          "intensity_percent": 0.93386,
          "id": ""
        },
        {
          "energy_keV": 491.7,
          "absolute_intensity": 0.0050217,
          "intensity_percent": 0.50217,
          "id": ""
        },
        {
          "energy_keV": 681.9,
          "absolute_intensity": 0.0054622,
          "intensity_percent": 0.54622,
          "id": ""
        },
        {
          "energy_keV": 838.9,
          "absolute_intensity": 0.0093386,
          "intensity_percent": 0.93386,
          "id": ""
        }
      ]
    }
  ],
  "_metadata": {
    "source": "sandia.decay.xml",
    "description": "Nuclear decay data from Sandia National Laboratories",
    "has_gamma_emissions": true,
    "num_decay_modes": 1,
    "num_gamma_lines": 89
  }
}